{
  "sections": {
    "main": {
      "type": "main-page",
      "disabled": true,
      "settings": {
        "text_alignment": "center"
      }
    },
    "download_file_list_aTzLDn": {
      "type": "download-file-list",
      "blocks": {
        "download_item_9dWkt9": {
          "type": "download_item",
          "settings": {
            "title": "Acid Dye Instructions",
            "download_label": "Download",
            "file_download": "https:\/\/cdn.shopify.com\/s\/files\/1\/0702\/7349\/9384\/files\/Group_11-1.png?v=1718070308"
          }
        }
      },
      "block_order": [
        "download_item_9dWkt9"
      ],
      "settings": {
        "title": "Instructions",
        "heading_size": "h2",
        "text": "<p>Instruction sheets can also be found under individual products below the product image, under the 'Instructions'<\/p>",
        "heading_position": "center",
        "padding_top": 72,
        "padding_bottom": 72,
        "padding_top_mobile": 48,
        "padding_bottom_mobile": 48
      }
    }
  },
  "order": [
    "main",
    "download_file_list_aTzLDn"
  ]
}
